fastcommit/__init__.py
fastcommit/__main__.py
fastcommit/config.py
fastcommit/core.py
fastcommit/main.py
fastcommit/system_prompt_en.txt
fastcommit/system_prompt_zh.txt
fastcommit-0.0.9.dist-info/LICENSE
fastcommit-0.0.9.dist-info/METADATA
fastcommit-0.0.9.dist-info/WHEEL
fastcommit-0.0.9.dist-info/entry_points.txt
fastcommit-0.0.9.dist-info/RECORD
